keypair_kinetic_sdk/__init__.py
keypair_kinetic_sdk/keypair/__init__.py
keypair_kinetic_sdk-0.1.1.dist-info/WHEEL
keypair_kinetic_sdk-0.1.1.dist-info/METADATA
keypair_kinetic_sdk-0.1.1.dist-info/RECORD
