Metadata-Version: 2.1
Name: keypair-kinetic-sdk
Version: 0.1.1
Summary: 
Author: Antoni Oktha Fernandes
Author-email: 37358597+DesKaOne@users.noreply.github.com
Requires-Python: >=3.8,<4.0
Classifier: Programming Language :: Python :: 3
Classifier: Programming Language :: Python :: 3.8
Classifier: Programming Language :: Python :: 3.9
Classifier: Programming Language :: Python :: 3.10
Classifier: Programming Language :: Python :: 3.11
Requires-Dist: bip-utils (>=2.7.0,<3.0.0)
Requires-Dist: pybase64 (>=1.2.3,<2.0.0)
Requires-Dist: pybip39 (>=0.1.0,<0.2.0)
Requires-Dist: python-dateutil (>=2.8.2,<3.0.0)
Requires-Dist: solana (>=0.28.0,<0.29.0)
